sweetconnect_api/__init__.py
sweetconnect_api/__main__.py
sweetconnect_api/py.typed
sweetconnect_api-0.0.1.dist-info/entry_points.txt
sweetconnect_api-0.0.1.dist-info/LICENSE
sweetconnect_api-0.0.1.dist-info/WHEEL
sweetconnect_api-0.0.1.dist-info/METADATA
sweetconnect_api-0.0.1.dist-info/RECORD
