Metadata-Version: 2.1
Name: sweetconnect-api
Version: 0.0.1
Summary: A SweetConnect API library for Python
Home-page: https://gitlab.com/sweetconnect/public/sweetconnect-api
License: GPL-3.0
Author: Kai CLauss
Author-email: kc@sweetconnect.io
Requires-Python: >=3.7,<4.0
Classifier: License :: OSI Approved :: GNU General Public License v3 (GPLv3)
Classifier: Programming Language :: Python :: 3
Classifier: Programming Language :: Python :: 3.10
Classifier: Programming Language :: Python :: 3.7
Classifier: Programming Language :: Python :: 3.8
Classifier: Programming Language :: Python :: 3.9
Requires-Dist: click (>=8.0.1)
Project-URL: Repository, https://gitlab.com/sweetconnect/public/sweetconnect-api
